scrapinghub/VERSION
scrapinghub/__init__.py
scrapinghub/legacy.py
scrapinghub/client/__init__.py
scrapinghub/client/activity.py
scrapinghub/client/collections.py
scrapinghub/client/exceptions.py
scrapinghub/client/frontiers.py
scrapinghub/client/items.py
scrapinghub/client/jobs.py
scrapinghub/client/logs.py
scrapinghub/client/projects.py
scrapinghub/client/proxy.py
scrapinghub/client/requests.py
scrapinghub/client/samples.py
scrapinghub/client/spiders.py
scrapinghub/client/utils.py
scrapinghub/hubstorage/__init__.py
scrapinghub/hubstorage/activity.py
scrapinghub/hubstorage/batchuploader.py
scrapinghub/hubstorage/client.py
scrapinghub/hubstorage/collectionsrt.py
scrapinghub/hubstorage/frontier.py
scrapinghub/hubstorage/job.py
scrapinghub/hubstorage/jobq.py
scrapinghub/hubstorage/project.py
scrapinghub/hubstorage/resourcetype.py
scrapinghub/hubstorage/serialization.py
scrapinghub/hubstorage/utils.py
scrapinghub-2.4.0.dist-info/LICENSE
scrapinghub-2.4.0.dist-info/METADATA
scrapinghub-2.4.0.dist-info/WHEEL
scrapinghub-2.4.0.dist-info/top_level.txt
scrapinghub-2.4.0.dist-info/RECORD
